wysdom/__init__.py
wysdom/__version__.py
wysdom/exceptions.py
wysdom/base_schema/Schema.py
wysdom/base_schema/SchemaAnything.py
wysdom/base_schema/SchemaConst.py
wysdom/base_schema/SchemaEnum.py
wysdom/base_schema/SchemaNone.py
wysdom/base_schema/SchemaPattern.py
wysdom/base_schema/SchemaPrimitive.py
wysdom/base_schema/SchemaType.py
wysdom/base_schema/__init__.py
wysdom/dom/DOMDict.py
wysdom/dom/DOMElement.py
wysdom/dom/DOMList.py
wysdom/dom/DOMObject.py
wysdom/dom/DOMProperties.py
wysdom/dom/__init__.py
wysdom/dom/functions.py
wysdom/mixins/ReadsJSON.py
wysdom/mixins/ReadsYAML.py
wysdom/mixins/RegistersSubclasses.py
wysdom/mixins/__init__.py
wysdom/object_schema/SchemaAnyOf.py
wysdom/object_schema/SchemaArray.py
wysdom/object_schema/SchemaDict.py
wysdom/object_schema/SchemaObject.py
wysdom/object_schema/__init__.py
wysdom/object_schema/resolve_arg_to_type.py
wysdom/user_objects/DictProperty.py
wysdom/user_objects/ListProperty.py
wysdom/user_objects/UserObject.py
wysdom/user_objects/UserProperty.py
wysdom/user_objects/__init__.py
wysdom/user_objects/functions.py
wysdom-0.3.0.dist-info/LICENSE
wysdom-0.3.0.dist-info/METADATA
wysdom-0.3.0.dist-info/WHEEL
wysdom-0.3.0.dist-info/top_level.txt
wysdom-0.3.0.dist-info/RECORD
