Metadata-Version: 2.1
Name: wysdom
Version: 0.3.0
Summary: A Python library for building custom document object models (DOMs) with built-in JSON schema checking
Home-page: https://github.com/jetavator/wysdom
Author: Joe Taylor
Author-email: joetaylorconsulting@gmail.com
License: UNKNOWN
Project-URL: Documentation, https://wysdom.readthedocs.io/en/latest/
Platform: UNKNOWN
Classifier: Programming Language :: Python
Classifier: Programming Language :: Python :: 3
Classifier: Programming Language :: Python :: 3.7
Classifier: License :: OSI Approved :: Apache Software License
Classifier: Operating System :: OS Independent
Classifier: Intended Audience :: Developers
Classifier: Topic :: Software Development :: Libraries :: Python Modules
Requires-Python: >=3.7.0
Requires-Dist: jsonschema (<4,>=3.2)
Requires-Dist: pyyaml (<6,>=5.3)
Provides-Extra: dev
Requires-Dist: coverage (<6,>=5.5) ; extra == 'dev'
Requires-Dist: wheel (<0.37,>=0.36.2) ; extra == 'dev'
Requires-Dist: sphinx (<4,>=3.5) ; extra == 'dev'
Requires-Dist: sphinx-rtd-theme (<0.6,>=0.5.1) ; extra == 'dev'
Requires-Dist: behave (<2,>=1.2.6) ; extra == 'dev'
